out/FishType.py
out/__init__.py
tests/__init__.py
tests/fish_obj.py
tests/test_typegen_cli.py
typegen/__init__.py
typegen/generate.py
typegen/main.py
typegen-0.1.2.dist-info/METADATA
typegen-0.1.2.dist-info/WHEEL
typegen-0.1.2.dist-info/entry_points.txt
typegen-0.1.2.dist-info/RECORD
