Metadata-Version: 2.1
Name: typegen
Version: 0.1.2
Summary: Auto generate typed dicts.
Home-page: https://github.com/pestosoftware/typegen
Author: Thomas Staats
Author-email: thomas.staats443@gmail.com
Requires-Python: >=3.8,<3.11
Classifier: Programming Language :: Python :: 3
Classifier: Programming Language :: Python :: 3.8
Classifier: Programming Language :: Python :: 3.9
Classifier: Programming Language :: Python :: 3.10
Requires-Dist: rich (>=13.5.2,<14.0.0)
